{"url":"https://americanhealthcarecapital.com/category/news/","title":"American Healthcare Capital Blog | M&amp;A Healthcare Advisors","content":"# Blog","contentType":"markdown","metadata":{"timestamp":"2025-06-12T15:10:55.191Z","status":200,"headers":{"date":"Thu, 12 Jun 2025 15:15:43 GMT","content-type":"text/html; charset=UTF-8","transfer-encoding":"chunked","connection":"keep-alive","vary":"Accept-Encoding, Accept-Encoding, Accept-Encoding, Accept-Encoding,Cookie","link":"<https://americanhealthcarecapital.com/wp-json/>; rel=\"https://api.w.org/\"","x-powered-by":"WP Engine","x-cacheable":"SHORT","cache-control":"max-age=600, must-revalidate","x-cache":"HIT: 7","x-cache-group":"normal","cf-cache-status":"DYNAMIC","set-cookie":"__cf_bm=2lIED4Q4AF5P0oGr1VidmZolw9hEWNQR0w1aMT.vyaE-1749741343-1.0.1.1-BL68Ghk4ebazOxYn7Z2Bl5iq8CQnNwtDLOX0Ma6my9T4qdwNYuTJttVwuH_Y0EupQn7fdCeE4DX6BLTdt2GuYTq6uleh.x5tTFVZxNBU7FE; path=/; expires=Thu, 12-Jun-25 15:45:43 GMT; domain=.americanhealthcarecapital.com; HttpOnly; Secure; SameSite=None","server":"cloudflare","cf-ray":"94ea4e1f4b2760fe-LHR","alt-svc":"h3=\":443\"; ma=86400"},"loadTime":2018,"processingTime":3505954}}