{"url":"https://cloud.google.com/docs/data","title":"Data handling and analysis overview  |  Documentation  |  Google Cloud","content":"# Data analytics technologies\n\nDocumentation and resources for unlocking your data's potential and transforming it into actionable AI insights with Google Cloud products.\n\n## Explore data analytics in Google Cloud\n\nRead documentation and Cloud Architecture Center articles about data analytics products, capabilities, and procedures.\n\n## Training, blog articles, and more\n\nGo to training courses, blog articles, and other related resources.\n\n## Data analytics products by use case\n\nExpand sections or use the filter to find products and guides for typical use cases.","contentType":"markdown","metadata":{"timestamp":"2025-06-07T19:34:55.860Z","status":200,"headers":{},"loadTime":13588,"usedBrowser":true,"usedRateLimiting":true,"processingTime":13908}}